dash_quill/Quill.py
dash_quill/__init__.py
dash_quill/_imports_.py
dash_quill/async-Quill.js
dash_quill/async-Quill.js.map
dash_quill/dash_quill.min.js
dash_quill/dash_quill.min.js.map
dash_quill/metadata.json
dash_quill/package-info.json
dash_quill-0.0.4.dist-info/LICENSE
dash_quill-0.0.4.dist-info/METADATA
dash_quill-0.0.4.dist-info/WHEEL
dash_quill-0.0.4.dist-info/top_level.txt
dash_quill-0.0.4.dist-info/RECORD
